vid2slides/__init__.py
vid2slides/cli.py
vid2slides/vid2slides.py
vid2slides-0.0.4.dist-info/LICENSE
vid2slides-0.0.4.dist-info/METADATA
vid2slides-0.0.4.dist-info/WHEEL
vid2slides-0.0.4.dist-info/entry_points.txt
vid2slides-0.0.4.dist-info/top_level.txt
vid2slides-0.0.4.dist-info/RECORD
